MANIFEST.in
setup.py
justpith/__init__.py
justpith/logger/__init__.py
justpith/logger/logger.py
justpith/logger/logging.yaml
justpith/mongo/__init__.py
justpith/mongo/mongo.py
justpith/mongo/common/__init__.py
justpith/mongo/common/mongo_common.py
justpith/mongo/controller/__init__.py
justpith/mongo/controller/mongo_controller.py
justpith/mongo/factorizer/__init__.py
justpith/mongo/factorizer/mongo_factorizer.py
justpith/mongo/news_consumer/__init__.py
justpith/mongo/news_consumer/mongo_news_consumer.py
justpith/mongo/reccomender/__init__.py
justpith/mongo/reccomender/mongo_reccomender.py
justpith/mongo/teacher/__init__.py
justpith/mongo/teacher/mongo_teacher.py
justpith/mongo/web_app/__init__.py
justpith/mongo/web_app/mongo_web_app.py
justpith/rabbit/__init__.py
justpith/rabbit/rabbit.py
justpith/rabbit/rabbit_setting.py
justpith/rabbit/receiver.py
justpith/rabbit/sender.py
justpith/util/__init__.py
justpith/util/util.py
justpith_docker.egg-info/PKG-INFO
justpith_docker.egg-info/SOURCES.txt
justpith_docker.egg-info/dependency_links.txt
justpith_docker.egg-info/not-zip-safe
justpith_docker.egg-info/requires.txt
justpith_docker.egg-info/top_level.txt