Metadata-Version: 1.0
Name: justpith-docker
Version: 1.0.2.59
Summary: Core code for justpith infrastructure
Home-page: http://packages.python.org/justpith
Author: Antonio Carisita
Author-email: a.caristia@gmail.com
License: GPL
Keywords: justpith's core
Platform: UNKNOWN
